<odoo>
    <data noupdate="1">
        <record id="practicing_scedule_action_id" model="ir.cron">
            <field name="name">Practice Scedule Action</field>
            <field name="model_id" ref="model_shopping_customer"/>
            <field name="state">code</field>
            <field name="code">model.start_scedule_action()</field>
            <field name='interval_number'>1</field>
            <field name='interval_type'>minutes</field>
            <field name="numbercall">-1</field>
            <field name="priority">3</field>
        </record>
    </data>
</odoo>